{"version": {"major": 1, "minor": 0}, "type": "Multiple points", "points": [{"point": [237, 165, 183], "name": "tumor"}, {"point": [237, 182, 182], "name": "tumor"}, {"point": [242, 178, 184], "name": "tumor"}, {"point": [234, 180, 178], "name": "tumor"}, {"point": [240, 163, 174], "name": "tumor"}, {"point": [238, 152, 183], "name": "tumor"}, {"point": [237, 170, 176], "name": "tumor"}, {"point": [246, 173, 187], "name": "tumor"}, {"point": [236, 183, 180], "name": "tumor"}, {"point": [245, 170, 180], "name": "tumor"}, {"point": [219, 176, 182], "name": "background"}, {"point": [162, 189, 142], "name": "background"}, {"point": [213, 187, 201], "name": "background"}, {"point": [186, 233, 139], "name": "background"}, {"point": [206, 212, 192], "name": "background"}, {"point": [200, 192, 185], "name": "background"}, {"point": [213, 224, 172], "name": "background"}, {"point": [160, 239, 0], "name": "background"}, {"point": [207, 199, 193], "name": "background"}, {"point": [158, 199, 105], "name": "background"}]}