{"version": {"major": 1, "minor": 0}, "type": "Multiple points", "points": [{"point": [223, 185, 476], "name": "background"}, {"point": [201, 210, 416], "name": "background"}, {"point": [224, 210, 167], "name": "background"}, {"point": [202, 214, 341], "name": "background"}, {"point": [187, 202, 367], "name": "background"}, {"point": [193, 249, 547], "name": "background"}, {"point": [150, 214, 316], "name": "background"}, {"point": [251, 208, 394], "name": "background"}, {"point": [189, 207, 457], "name": "background"}, {"point": [188, 188, 438], "name": "background"}]}