{"version": {"major": 1, "minor": 0}, "type": "Multiple points", "points": [{"point": [145, 231, 155], "name": "tumor"}, {"point": [182, 176, 185], "name": "tumor"}, {"point": [264, 218, 148], "name": "tumor"}, {"point": [183, 178, 189], "name": "tumor"}, {"point": [262, 220, 159], "name": "tumor"}, {"point": [181, 196, 184], "name": "tumor"}, {"point": [216, 205, 184], "name": "tumor"}, {"point": [168, 178, 189], "name": "tumor"}, {"point": [143, 230, 158], "name": "tumor"}, {"point": [181, 180, 185], "name": "tumor"}, {"point": [175, 180, 2], "name": "background"}, {"point": [169, 198, 137], "name": "background"}, {"point": [147, 206, 120], "name": "background"}, {"point": [141, 220, 122], "name": "background"}, {"point": [172, 221, 151], "name": "background"}, {"point": [139, 221, 144], "name": "background"}, {"point": [146, 226, 127], "name": "background"}, {"point": [181, 224, 128], "name": "background"}, {"point": [252, 194, 133], "name": "background"}, {"point": [162, 218, 154], "name": "background"}]}