{"version": {"major": 1, "minor": 0}, "type": "Multiple points", "points": [{"point": [169, 201, 175], "name": "tumor"}, {"point": [171, 204, 177], "name": "tumor"}, {"point": [171, 199, 177], "name": "tumor"}, {"point": [167, 199, 176], "name": "tumor"}, {"point": [172, 197, 174], "name": "tumor"}, {"point": [170, 199, 177], "name": "tumor"}, {"point": [167, 202, 177], "name": "tumor"}, {"point": [171, 204, 177], "name": "tumor"}, {"point": [172, 203, 177], "name": "tumor"}, {"point": [170, 201, 174], "name": "tumor"}, {"point": [158, 173, 161], "name": "background"}, {"point": [260, 262, 325], "name": "background"}, {"point": [155, 159, 175], "name": "background"}, {"point": [148, 203, 144], "name": "background"}, {"point": [249, 265, 325], "name": "background"}, {"point": [161, 167, 140], "name": "background"}, {"point": [158, 184, 151], "name": "background"}, {"point": [214, 203, 84], "name": "background"}, {"point": [172, 170, 163], "name": "background"}, {"point": [159, 177, 156], "name": "background"}]}