{"version": {"major": 1, "minor": 0}, "type": "Multiple points", "points": [{"point": [189, 213, 265], "name": "tumor"}, {"point": [188, 203, 223], "name": "tumor"}, {"point": [197, 213, 223], "name": "tumor"}, {"point": [186, 205, 273], "name": "tumor"}, {"point": [198, 198, 244], "name": "tumor"}, {"point": [192, 205, 270], "name": "tumor"}, {"point": [220, 161, 94], "name": "tumor"}, {"point": [195, 162, 164], "name": "tumor"}, {"point": [197, 183, 131], "name": "tumor"}, {"point": [186, 168, 90], "name": "tumor"}, {"point": [196, 205, 145], "name": "background"}, {"point": [118, 273, 325], "name": "background"}, {"point": [230, 192, 244], "name": "background"}, {"point": [107, 271, 324], "name": "background"}, {"point": [177, 152, 0], "name": "background"}, {"point": [208, 145, 160], "name": "background"}, {"point": [253, 155, 72], "name": "background"}, {"point": [196, 155, 160], "name": "background"}, {"point": [251, 171, 2], "name": "background"}, {"point": [217, 169, 182], "name": "background"}]}