{"version": {"major": 1, "minor": 0}, "type": "Multiple points", "points": [{"point": [206, 199, 277], "name": "tumor"}, {"point": [211, 199, 287], "name": "tumor"}, {"point": [168, 216, 224], "name": "tumor"}, {"point": [206, 248, 318], "name": "tumor"}, {"point": [187, 184, 254], "name": "tumor"}, {"point": [208, 195, 267], "name": "tumor"}, {"point": [170, 212, 235], "name": "tumor"}, {"point": [173, 209, 230], "name": "tumor"}, {"point": [194, 205, 395], "name": "tumor"}, {"point": [180, 183, 250], "name": "tumor"}, {"point": [244, 196, 260], "name": "background"}, {"point": [208, 212, 351], "name": "background"}, {"point": [207, 183, 255], "name": "background"}, {"point": [160, 202, 267], "name": "background"}, {"point": [200, 210, 342], "name": "background"}, {"point": [168, 202, 223], "name": "background"}, {"point": [240, 197, 249], "name": "background"}, {"point": [201, 184, 360], "name": "background"}, {"point": [241, 210, 272], "name": "background"}, {"point": [200, 197, 351], "name": "background"}]}