{"version": {"major": 1, "minor": 0}, "type": "Multiple points", "points": [{"point": [239, 257, 126], "name": "background"}, {"point": [240, 191, 1], "name": "background"}, {"point": [219, 158, 156], "name": "background"}, {"point": [196, 220, 256], "name": "background"}, {"point": [195, 217, 136], "name": "background"}, {"point": [234, 228, 170], "name": "background"}, {"point": [210, 186, 135], "name": "background"}, {"point": [229, 220, 283], "name": "background"}, {"point": [214, 179, 152], "name": "background"}, {"point": [229, 163, 185], "name": "background"}]}