{"version": {"major": 1, "minor": 0}, "type": "Multiple points", "points": [{"point": [207, 168, 2], "name": "background"}, {"point": [188, 171, 138], "name": "background"}, {"point": [213, 234, 268], "name": "background"}, {"point": [201, 152, 164], "name": "background"}, {"point": [203, 220, 262], "name": "background"}, {"point": [241, 207, 0], "name": "background"}, {"point": [200, 159, 2], "name": "background"}, {"point": [212, 194, 159], "name": "background"}, {"point": [123, 178, 212], "name": "background"}, {"point": [136, 200, 227], "name": "background"}]}