{"version": {"major": 1, "minor": 0}, "type": "Multiple points", "points": [{"point": [174, 227, 165], "name": "tumor"}, {"point": [216, 204, 226], "name": "tumor"}, {"point": [263, 209, 172], "name": "tumor"}, {"point": [267, 208, 166], "name": "tumor"}, {"point": [236, 167, 200], "name": "tumor"}, {"point": [176, 228, 165], "name": "tumor"}, {"point": [213, 197, 226], "name": "tumor"}, {"point": [261, 212, 172], "name": "tumor"}, {"point": [291, 193, 159], "name": "tumor"}, {"point": [232, 170, 196], "name": "tumor"}, {"point": [197, 207, 137], "name": "background"}, {"point": [135, 181, 0], "name": "background"}, {"point": [232, 217, 141], "name": "background"}, {"point": [213, 218, 124], "name": "background"}, {"point": [160, 209, 94], "name": "background"}, {"point": [168, 215, 120], "name": "background"}, {"point": [203, 149, 102], "name": "background"}, {"point": [189, 167, 3], "name": "background"}, {"point": [199, 249, 235], "name": "background"}, {"point": [289, 167, 0], "name": "background"}]}