{"version": {"major": 1, "minor": 0}, "type": "Multiple points", "points": [{"point": [162, 182, 92], "name": "background"}, {"point": [219, 192, 89], "name": "background"}, {"point": [243, 218, 149], "name": "background"}, {"point": [238, 180, 239], "name": "background"}, {"point": [191, 180, 126], "name": "background"}, {"point": [242, 201, 311], "name": "background"}, {"point": [181, 180, 124], "name": "background"}, {"point": [232, 182, 93], "name": "background"}, {"point": [190, 182, 118], "name": "background"}, {"point": [187, 151, 213], "name": "background"}]}