{"version": {"major": 1, "minor": 0}, "type": "Multiple points", "points": [{"point": [115, 133, 50], "name": "tumor"}, {"point": [128, 136, 115], "name": "tumor"}, {"point": [130, 125, 92], "name": "tumor"}, {"point": [141, 110, 57], "name": "tumor"}, {"point": [139, 122, 122], "name": "tumor"}, {"point": [111, 113, 85], "name": "tumor"}, {"point": [178, 155, 164], "name": "tumor"}, {"point": [118, 127, 107], "name": "tumor"}, {"point": [144, 113, 62], "name": "tumor"}, {"point": [119, 94, 69], "name": "tumor"}, {"point": [167, 127, 107], "name": "background"}, {"point": [75, 113, 151], "name": "background"}, {"point": [117, 120, 154], "name": "background"}, {"point": [80, 123, 157], "name": "background"}, {"point": [92, 101, 153], "name": "background"}, {"point": [81, 115, 155], "name": "background"}, {"point": [92, 127, 148], "name": "background"}, {"point": [88, 119, 153], "name": "background"}, {"point": [99, 111, 164], "name": "background"}, {"point": [141, 140, 247], "name": "background"}]}