{"version": {"major": 1, "minor": 0}, "type": "Multiple points", "points": [{"point": [139, 115, 95], "name": "tumor"}, {"point": [121, 130, 131], "name": "tumor"}, {"point": [104, 117, 95], "name": "tumor"}, {"point": [132, 93, 85], "name": "tumor"}, {"point": [119, 127, 119], "name": "tumor"}, {"point": [137, 116, 96], "name": "tumor"}, {"point": [122, 130, 132], "name": "tumor"}, {"point": [105, 119, 96], "name": "tumor"}, {"point": [133, 96, 84], "name": "tumor"}, {"point": [118, 127, 120], "name": "tumor"}, {"point": [128, 151, 183], "name": "background"}, {"point": [115, 131, 181], "name": "background"}, {"point": [140, 124, 141], "name": "background"}, {"point": [125, 162, 277], "name": "background"}, {"point": [114, 133, 182], "name": "background"}, {"point": [115, 135, 190], "name": "background"}, {"point": [142, 123, 144], "name": "background"}, {"point": [100, 136, 288], "name": "background"}, {"point": [116, 135, 188], "name": "background"}, {"point": [127, 143, 183], "name": "background"}]}