{"version": {"major": 1, "minor": 0}, "type": "Multiple points", "points": [{"point": [76, 108, 300], "name": "tumor"}, {"point": [96, 81, 334], "name": "tumor"}, {"point": [107, 74, 275], "name": "tumor"}, {"point": [136, 89, 247], "name": "tumor"}, {"point": [72, 81, 294], "name": "tumor"}, {"point": [86, 78, 109], "name": "tumor"}, {"point": [131, 88, 308], "name": "tumor"}, {"point": [101, 119, 287], "name": "tumor"}, {"point": [99, 104, 389], "name": "tumor"}, {"point": [91, 75, 303], "name": "tumor"}, {"point": [135, 98, 271], "name": "background"}, {"point": [77, 105, 214], "name": "background"}, {"point": [113, 110, 397], "name": "background"}, {"point": [127, 97, 184], "name": "background"}, {"point": [119, 102, 149], "name": "background"}, {"point": [98, 93, 342], "name": "background"}, {"point": [99, 102, 72], "name": "background"}, {"point": [81, 76, 217], "name": "background"}, {"point": [73, 113, 265], "name": "background"}, {"point": [91, 119, 377], "name": "background"}]}