{"version": {"major": 1, "minor": 0}, "type": "Multiple points", "points": [{"point": [105, 123, 170], "name": "background"}, {"point": [124, 147, 244], "name": "background"}, {"point": [98, 96, 134], "name": "background"}, {"point": [98, 105, 165], "name": "background"}, {"point": [79, 101, 139], "name": "background"}, {"point": [133, 152, 244], "name": "background"}, {"point": [110, 126, 153], "name": "background"}, {"point": [84, 133, 149], "name": "background"}, {"point": [154, 137, 262], "name": "background"}, {"point": [112, 98, 159], "name": "background"}]}