{"version": {"major": 1, "minor": 0}, "type": "Multiple points", "points": [{"point": [108, 95, 359], "name": "tumor"}, {"point": [137, 98, 340], "name": "tumor"}, {"point": [136, 102, 326], "name": "tumor"}, {"point": [119, 101, 360], "name": "tumor"}, {"point": [121, 108, 354], "name": "tumor"}, {"point": [89, 107, 361], "name": "tumor"}, {"point": [96, 88, 199], "name": "tumor"}, {"point": [72, 116, 291], "name": "tumor"}, {"point": [101, 122, 283], "name": "tumor"}, {"point": [94, 94, 191], "name": "tumor"}, {"point": [118, 100, 328], "name": "background"}, {"point": [97, 101, 354], "name": "background"}, {"point": [118, 91, 241], "name": "background"}, {"point": [79, 121, 191], "name": "background"}, {"point": [117, 99, 326], "name": "background"}, {"point": [92, 122, 213], "name": "background"}, {"point": [89, 97, 250], "name": "background"}, {"point": [73, 84, 374], "name": "background"}, {"point": [129, 106, 353], "name": "background"}, {"point": [83, 85, 236], "name": "background"}]}