{"version": {"major": 1, "minor": 0}, "type": "Multiple points", "points": [{"point": [73, 63, 149], "name": "tumor"}, {"point": [57, 89, 62], "name": "tumor"}, {"point": [52, 79, 123], "name": "tumor"}, {"point": [72, 61, 123], "name": "tumor"}, {"point": [109, 71, 71], "name": "tumor"}, {"point": [88, 68, 132], "name": "tumor"}, {"point": [84, 87, 176], "name": "tumor"}, {"point": [52, 93, 121], "name": "tumor"}, {"point": [124, 77, 139], "name": "tumor"}, {"point": [58, 76, 71], "name": "tumor"}, {"point": [81, 73, 109], "name": "background"}, {"point": [68, 78, 121], "name": "background"}, {"point": [68, 92, 112], "name": "background"}, {"point": [83, 72, 112], "name": "background"}, {"point": [67, 97, 186], "name": "background"}, {"point": [64, 89, 100], "name": "background"}, {"point": [86, 94, 108], "name": "background"}, {"point": [79, 102, 103], "name": "background"}, {"point": [73, 77, 120], "name": "background"}, {"point": [75, 73, 114], "name": "background"}]}