{"version": {"major": 1, "minor": 0}, "type": "Multiple points", "points": [{"point": [124, 106, 120], "name": "tumor"}, {"point": [78, 144, 103], "name": "tumor"}, {"point": [160, 111, 220], "name": "tumor"}, {"point": [122, 141, 249], "name": "tumor"}, {"point": [122, 137, 246], "name": "tumor"}, {"point": [148, 94, 235], "name": "tumor"}, {"point": [143, 130, 244], "name": "tumor"}, {"point": [123, 116, 209], "name": "tumor"}, {"point": [95, 111, 104], "name": "tumor"}, {"point": [116, 89, 200], "name": "tumor"}, {"point": [164, 111, 169], "name": "background"}, {"point": [91, 134, 158], "name": "background"}, {"point": [104, 144, 158], "name": "background"}, {"point": [88, 132, 157], "name": "background"}, {"point": [119, 148, 171], "name": "background"}, {"point": [160, 123, 157], "name": "background"}, {"point": [109, 144, 165], "name": "background"}, {"point": [124, 151, 171], "name": "background"}, {"point": [123, 154, 169], "name": "background"}, {"point": [78, 141, 163], "name": "background"}]}