{"version": {"major": 1, "minor": 0}, "type": "Multiple points", "points": [{"point": [121, 91, 207], "name": "tumor"}, {"point": [119, 134, 66], "name": "tumor"}, {"point": [121, 94, 207], "name": "tumor"}, {"point": [120, 134, 67], "name": "tumor"}, {"point": [119, 88, 208], "name": "tumor"}, {"point": [118, 134, 66], "name": "tumor"}, {"point": [122, 91, 209], "name": "tumor"}, {"point": [119, 135, 67], "name": "tumor"}, {"point": [123, 92, 206], "name": "tumor"}, {"point": [118, 135, 66], "name": "tumor"}, {"point": [93, 129, 176], "name": "background"}, {"point": [113, 117, 185], "name": "background"}, {"point": [89, 120, 173], "name": "background"}, {"point": [123, 119, 80], "name": "background"}, {"point": [103, 144, 178], "name": "background"}, {"point": [114, 122, 178], "name": "background"}, {"point": [95, 107, 176], "name": "background"}, {"point": [104, 159, 169], "name": "background"}, {"point": [129, 120, 64], "name": "background"}, {"point": [138, 144, 174], "name": "background"}]}