{"version": {"major": 1, "minor": 0}, "type": "Multiple points", "points": [{"point": [100, 94, 71], "name": "tumor"}, {"point": [108, 94, 112], "name": "tumor"}, {"point": [104, 101, 156], "name": "tumor"}, {"point": [96, 86, 73], "name": "tumor"}, {"point": [97, 99, 126], "name": "tumor"}, {"point": [64, 104, 308], "name": "tumor"}, {"point": [86, 102, 101], "name": "tumor"}, {"point": [103, 101, 287], "name": "tumor"}, {"point": [98, 104, 306], "name": "tumor"}, {"point": [69, 102, 309], "name": "tumor"}, {"point": [87, 109, 380], "name": "background"}, {"point": [89, 97, 210], "name": "background"}, {"point": [89, 103, 101], "name": "background"}, {"point": [96, 98, 177], "name": "background"}, {"point": [80, 118, 225], "name": "background"}, {"point": [98, 116, 387], "name": "background"}, {"point": [93, 105, 182], "name": "background"}, {"point": [120, 112, 185], "name": "background"}, {"point": [88, 99, 213], "name": "background"}, {"point": [95, 108, 194], "name": "background"}]}