{"version": {"major": 1, "minor": 0}, "type": "Multiple points", "points": [{"point": [137, 109, 114], "name": "tumor"}, {"point": [137, 111, 115], "name": "tumor"}, {"point": [139, 113, 115], "name": "tumor"}, {"point": [135, 111, 116], "name": "tumor"}, {"point": [138, 112, 114], "name": "tumor"}, {"point": [138, 107, 114], "name": "tumor"}, {"point": [136, 107, 115], "name": "tumor"}, {"point": [139, 110, 115], "name": "tumor"}, {"point": [139, 111, 117], "name": "tumor"}, {"point": [138, 113, 115], "name": "tumor"}, {"point": [143, 127, 295], "name": "background"}, {"point": [119, 127, 155], "name": "background"}, {"point": [136, 137, 141], "name": "background"}, {"point": [101, 147, 201], "name": "background"}, {"point": [112, 152, 152], "name": "background"}, {"point": [100, 135, 293], "name": "background"}, {"point": [101, 118, 207], "name": "background"}, {"point": [120, 128, 160], "name": "background"}, {"point": [130, 134, 194], "name": "background"}, {"point": [115, 110, 196], "name": "background"}]}