{"version": {"major": 1, "minor": 0}, "type": "Multiple points", "points": [{"point": [79, 98, 202], "name": "tumor"}, {"point": [88, 92, 286], "name": "tumor"}, {"point": [80, 88, 241], "name": "tumor"}, {"point": [75, 95, 196], "name": "tumor"}, {"point": [82, 78, 253], "name": "tumor"}, {"point": [79, 97, 203], "name": "tumor"}, {"point": [89, 92, 286], "name": "tumor"}, {"point": [82, 87, 241], "name": "tumor"}, {"point": [76, 95, 196], "name": "tumor"}, {"point": [82, 79, 254], "name": "tumor"}, {"point": [54, 82, 249], "name": "background"}, {"point": [91, 82, 314], "name": "background"}, {"point": [49, 89, 233], "name": "background"}, {"point": [71, 84, 241], "name": "background"}, {"point": [95, 108, 310], "name": "background"}, {"point": [83, 80, 314], "name": "background"}, {"point": [97, 98, 308], "name": "background"}, {"point": [94, 94, 314], "name": "background"}, {"point": [74, 77, 314], "name": "background"}, {"point": [81, 78, 167], "name": "background"}]}